rxnlvl/__init__.py
rxnlvl/baseline.py
rxnlvl/edge.py
rxnlvl/energy.py
rxnlvl/level.py
rxnlvl/rxnlvl_util.py
rxnlvl-0.3.10.data/scripts/__init__.py
rxnlvl-0.3.10.dist-info/LICENSE
rxnlvl-0.3.10.dist-info/METADATA
rxnlvl-0.3.10.dist-info/WHEEL
rxnlvl-0.3.10.dist-info/top_level.txt
rxnlvl-0.3.10.dist-info/RECORD
