Metadata-Version: 2.1
Name: rxnlvl
Version: 0.3.10
Summary: A simple python package for drawing attractive chemical reaction energy level diagrams.
Home-page: https://github.com/steerapi/rxnlvl
Author: Surat Teerapittayanon
Author-email: steerapi@gmail.com
License: GPL
Platform: UNKNOWN
Classifier: Programming Language :: Python :: 3
Classifier: Operating System :: OS Independent
